dragon_e/__init__.py
dragon_e/_dragon_e.py
dragon_e/_hash.py
dragon_e/_image.py
dragon_e/_test.py
dragon_e-2.0.2.dist-info/LICENSE
dragon_e-2.0.2.dist-info/METADATA
dragon_e-2.0.2.dist-info/WHEEL
dragon_e-2.0.2.dist-info/top_level.txt
dragon_e-2.0.2.dist-info/RECORD
