Metadata-Version: 2.2
Name: dragon_e
Version: 2.0.2
Summary: Encrypt like a dragon: new method for securing data
Author-email: Wren <theminecommander@gmail.com>
Project-URL: Homepage, https://github.com/TheMineCommander/dragon_e
Project-URL: Issues, https://github.com/TheMineCommander/dragon_e/issues
Classifier: Programming Language :: Python :: 3
Classifier: License :: OSI Approved :: GNU Affero General Public License v3
Classifier: Operating System :: OS Independent
Requires-Python: >=3.8
License-File: LICENSE
